{
  "permalink": "/blog/welcome-to-devsecops-unlocked",
  "source": "@site/blog/2024-12-06-welcome-to-devsecops-unlocked.md",
  "title": "Welcome to DevSecOps Unlocked",
  "description": "Welcome to DevSecOps Unlocked – your comprehensive resource for bridging the gap between Development, Security, and Operations! 🚀🔒",
  "date": "2024-12-06T00:00:00.000Z",
  "tags": [
    {
      "inline": true,
      "label": "welcome",
      "permalink": "/blog/tags/welcome"
    },
    {
      "inline": true,
      "label": "devsecops",
      "permalink": "/blog/tags/devsecops"
    },
    {
      "inline": true,
      "label": "security",
      "permalink": "/blog/tags/security"
    },
    {
      "inline": true,
      "label": "devops",
      "permalink": "/blog/tags/devops"
    },
    {
      "inline": true,
      "label": "cloud",
      "permalink": "/blog/tags/cloud"
    }
  ],
  "readingTime": 1.62,
  "hasTruncateMarker": true,
  "authors": [
    {
      "name": "Reik Loeber",
      "title": "Fullstack Developer & DevOps & DevSecOps",
      "url": "https://github.com/reiloe",
      "imageURL": "https://github.com/reiloe.png",
      "key": "reiloe",
      "page": null
    }
  ],
  "frontMatter": {
    "slug": "welcome-to-devsecops-unlocked",
    "title": "Welcome to DevSecOps Unlocked",
    "authors": [
      "reiloe"
    ],
    "tags": [
      "welcome",
      "devsecops",
      "security",
      "devops",
      "cloud"
    ]
  },
  "unlisted": false,
  "nextItem": {
    "title": "Kubernetes Security Guide",
    "permalink": "/blog/kubernetes-security-best-practices"
  }
}